untappd_scraper/__init__.py
untappd_scraper/beer.py
untappd_scraper/brewery.py
untappd_scraper/client.py
untappd_scraper/html_session.py
untappd_scraper/logging_config.py
untappd_scraper/logs.yml
untappd_scraper/py.typed
untappd_scraper/user.py
untappd_scraper/user_beer_history.py
untappd_scraper/user_lists.py
untappd_scraper/user_lists_details.py
untappd_scraper/user_venue_history.py
untappd_scraper/venue.py
untappd_scraper/venue_menus.py
untappd_scraper/web.py
untappd_scraper/structs/__init__.py
untappd_scraper/structs/mixins.py
untappd_scraper/structs/other.py
untappd_scraper-0.15.1.dist-info/METADATA
untappd_scraper-0.15.1.dist-info/WHEEL
untappd_scraper-0.15.1.dist-info/licenses/LICENSE
untappd_scraper-0.15.1.dist-info/RECORD
