Metadata-Version: 2.4
Name: untappd-scraper
Version: 0.15.1
Summary: Scrape various Untappd web pages and return as parsed dataclasses
Author-email: Wardy <wardy3@gmail.com>
License: MIT License
License-File: LICENSE
Keywords: beer,scraper,untappd
Classifier: Development Status :: 4 - Beta
Classifier: Intended Audience :: Developers
Classifier: License :: OSI Approved :: MIT License
Classifier: Operating System :: OS Independent
Classifier: Programming Language :: Python :: 3
Classifier: Programming Language :: Python :: 3.14
Classifier: Topic :: Software Development :: Libraries :: Python Modules
Classifier: Typing :: Typed
Requires-Python: >=3.14
Requires-Dist: beautifulsoup4>=4.13.3
Requires-Dist: brotli>=1.1.0
Requires-Dist: haversine>=2.9.0
Requires-Dist: hishel[httpx]>=1.1.4
Requires-Dist: httpx[brotli,http2,zstd]>=0.28.1
Requires-Dist: logfire[httpx]>=3.14.1
Requires-Dist: loguru>=0.7.3
Requires-Dist: lxml[html-clean]>=5.3.2
Requires-Dist: parse>=1.20.2
Requires-Dist: pydantic>=2.12.4
Requires-Dist: python-dateutil>=2.9.0.post0
Requires-Dist: pyyaml>=6.0.2
Requires-Dist: ratelim>=0.1.6
Requires-Dist: requests-cache>=1.2.1
Requires-Dist: requests-html>=0.10.0
Requires-Dist: tenacity>=9.1.2
Requires-Dist: utpd-models-web>=0.3.0
